README.md
setup.py
pytest_xray/__init__.py
pytest_xray/constants.py
pytest_xray/models.py
pytest_xray/plugin.py
pytest_xray/utils.py
pytest_xray.egg-info/PKG-INFO
pytest_xray.egg-info/SOURCES.txt
pytest_xray.egg-info/dependency_links.txt
pytest_xray.egg-info/entry_points.txt
pytest_xray.egg-info/requires.txt
pytest_xray.egg-info/top_level.txt