Metadata-Version: 2.1
Name: pytest-xray
Version: 0.2.1
Summary: UNKNOWN
Home-page: UNKNOWN
Author: Neville Tummon
Author-email: nt.devs@gmail.com
License: UNKNOWN
Download-URL: https://github.com/Isentia/pytest_xray/archive/v0.2.1.tar.gz
Platform: UNKNOWN
Classifier: Development Status :: 3 - Alpha
Classifier: Intended Audience :: Developers
Classifier: Topic :: Software Development :: Testing
Classifier: License :: OSI Approved :: MIT License
Classifier: Programming Language :: Python :: 3
Classifier: Programming Language :: Python :: 3.6
Classifier: Programming Language :: Python :: 3.7
Classifier: Programming Language :: Python :: Implementation :: CPython
Requires-Python: >=3.6.6
